pytraders/__init__.py
pytraders-0.0.4.dist-info/LICENSE
pytraders-0.0.4.dist-info/METADATA
pytraders-0.0.4.dist-info/WHEEL
pytraders-0.0.4.dist-info/top_level.txt
pytraders-0.0.4.dist-info/RECORD
