Metadata-Version: 2.1
Name: pytraders
Version: 0.0.4
Summary: A Python package to get trading indicators.
Home-page: https://github.com/Akil1996/pytrades
Author: Akil Thangavel
Author-email: akilh4@gmail.com
License: MIT
Platform: UNKNOWN
Classifier: License :: OSI Approved :: MIT License
Classifier: Operating System :: OS Independent
Classifier: Programming Language :: Python :: 3
Classifier: Programming Language :: Python :: 3.7
Classifier: Programming Language :: Python :: 3.8
Classifier: Programming Language :: Python :: 3.9
Requires-Dist: numpy
